funapi/__init__.py
funchat-0.0.1.dist-info/LICENSE
funchat-0.0.1.dist-info/METADATA
funchat-0.0.1.dist-info/WHEEL
funchat-0.0.1.dist-info/entry_points.txt
funchat-0.0.1.dist-info/top_level.txt
funchat-0.0.1.dist-info/RECORD
